aiocoalesce/__init__.py
aiocoalesce/core.py
aiocoalesce-0.1.0.dist-info/METADATA
aiocoalesce-0.1.0.dist-info/WHEEL
aiocoalesce-0.1.0.dist-info/RECORD
