Metadata-Version: 2.4
Name: aiocoalesce
Version: 0.1.0
Summary: A best-in-class async request coalescing library for Python.
Requires-Python: >=3.9
Provides-Extra: dev
Requires-Dist: pytest; extra == 'dev'
Requires-Dist: pytest-asyncio; extra == 'dev'
